setup.py
PunkyBrowster.egg-info/PKG-INFO
PunkyBrowster.egg-info/SOURCES.txt
PunkyBrowster.egg-info/dependency_links.txt
PunkyBrowster.egg-info/top_level.txt
punky/__init__.py
punky/browster.py