Metadata-Version: 1.0
Name: PunkyBrowster
Version: 0.3.1
Summary: Programmatic web browsing module
Home-page: http://bitbucket.org/leapfrogdevelopment/punkybrowster/
Author: Leapfrog Direct Response LLC
Author-email: UNKNOWN
License: GNU Public License v3.0
Platform: UNKNOWN
Classifier: Development Status :: 4 - Beta
Classifier: Intended Audience :: Developers
Classifier: License :: OSI Approved :: GNU General Public License (GPL)
Classifier: Natural Language :: English
Classifier: Operating System :: POSIX
Classifier: Operating System :: Microsoft :: Windows
Classifier: Programming Language :: Python
Classifier: Topic :: Internet :: WWW/HTTP
